{"ModuleName":"Decisions","IsIdentityProvider":null,"ModuleDependencies":null,"Version":"9.2.0.00001","RequiresLicense":false,"Description":"The Decisions.MessageQueues module is a common module that enables specific messaging modules.  This module cannot be used alone and only provides common behavior.","CompiledOnDate":"2024-08-20T07:10:01.3839386Z","CompiledOnServer":"rack16","ImagePath":null,"Installed":false,"InstalledVersion":null,"HideInFeaturesList":null,"IsGithubModule":false,"IsCustomModule":false}